calendar_fact/__init__.py
calendar_fact-1.2.0.dist-info/DESCRIPTION.rst
calendar_fact-1.2.0.dist-info/METADATA
calendar_fact-1.2.0.dist-info/RECORD
calendar_fact-1.2.0.dist-info/WHEEL
calendar_fact-1.2.0.dist-info/entry_points.txt
calendar_fact-1.2.0.dist-info/metadata.json
calendar_fact-1.2.0.dist-info/top_level.txt
