Metadata-Version: 2.0
Name: calendar-fact
Version: 1.2.0
Summary: Generate calendar fact from xkcd.com/1930
Home-page: https://gitlab.com/uda/calendar-fact
Author: Yehuda Deutsch
Author-email: yeh@uda.co.il
License: MIT
Platform: UNKNOWN
Classifier: Development Status :: 5 - Production/Stable
Classifier: Environment :: Console
Classifier: Intended Audience :: End Users/Desktop
Classifier: License :: OSI Approved :: MIT License
Classifier: Natural Language :: English
Classifier: Operating System :: OS Independent
Classifier: Programming Language :: Python
Classifier: Programming Language :: Python :: 3
Classifier: Programming Language :: Python :: 3.6
Classifier: Programming Language :: Python :: 3 :: Only
Requires-Python: >=3.6
